src/ALU.v
module ALU (
    input wire clk,
    input wire reset,
    input wire bit_in,
    input wire [2:0] op_select,

    output reg r0,
    output reg r1,
    output reg r2,
    output reg r3,
    output reg r4,
    output reg r5,
    output reg r6,

    output wire done
);

    // =========================
    // CONTADOR
    // =========================
    reg [3:0] count = 0;
    reg flag_14 = 0;

    always @(posedge clk or posedge reset) begin
        if (reset) begin
            count <= 0;
            flag_14 <= 0;
        end else begin
            if (count < 13) begin
                count <= count + 1;
                flag_14 <= 0;
            end else begin
                count <= 13;
                flag_14 <= 1;
            end
        end
    end

    assign done = flag_14;

    // =========================
    // REGISTROS
    // =========================
    reg [6:0] regA = 0;
    reg [6:0] regB = 0;
    reg [3:0] bit_count = 0;

    always @(posedge clk or posedge reset) begin
        if (reset) begin
            regA <= 0;
            regB <= 0;
            bit_count <= 0;
        end else begin
            if (!flag_14) begin
                if (bit_count < 7)
                    regA <= {regA[5:0], bit_in};
                else if (bit_count < 14)
                    regB <= {regB[5:0], bit_in};

                bit_count <= bit_count + 1;
            end
        end
    end

    // =========================
    // ALU (UNA SOLA VEZ)
    // =========================
    reg [6:0] result;
    reg executed = 0;

    always @(posedge clk or posedge reset) begin
        if (reset) begin
            result <= 0;
            executed <= 0;
        end else begin
            if (flag_14 && !executed) begin
                case (op_select)  // 🔥 USO DIRECTO
                    3'b000: result <= regA + regB;
                    3'b001: result <= regA & regB;
                    3'b010: result <= regA | regB;
                    3'b011: result <= regA ^ regB;
                    3'b100: result <= regA - regB;
                    default: result <= 0;
                endcase
                executed <= 1;
            end
        end
    end

    // =========================
    // SALIDAS
    // =========================
    always @(*) begin
        r0 = result[0];
        r1 = result[1];
        r2 = result[2];
        r3 = result[3];
        r4 = result[4];
        r5 = result[5];
        r6 = result[6];
    end

endmodule

src/ALU_tb.v
`timescale 1ns/1ps

module tb_ALU;

  reg clk;
  reg reset;
  reg bit_in;
  reg [2:0] op_select;

  wire r0, r1, r2, r3, r4, r5, r6;
  wire done;

  // DUT
  ALU uut (
    .clk(clk),
    .reset(reset),
    .bit_in(bit_in),
    .op_select(op_select),
    .r0(r0), .r1(r1), .r2(r2),
    .r3(r3), .r4(r4), .r5(r5), .r6(r6),
    .done(done)
  );

  // reloj
  always #5 clk = ~clk;

  // =========================
  // TAREA: RESET LIMPIO
  // =========================
  task do_reset;
  begin
    reset = 1;
    bit_in = 0;
    repeat(2) @(posedge clk); // asegurar limpieza
    reset = 0;
  end
  endtask

  // =========================
  // TAREA: ENVIAR DATOS
  // =========================
  task send_data;
    input [6:0] A;
    input [6:0] B;
    integer i;
    begin
      // A
      for (i = 6; i >= 0; i = i - 1) begin
        bit_in = A[i];
        @(posedge clk);
      end

      // B
      for (i = 6; i >= 0; i = i - 1) begin
        bit_in = B[i];
        @(posedge clk);
      end

      bit_in = 0; // importante después
    end
  endtask

  // =========================
  // MONITOR
  // =========================
  initial begin
    $monitor("t=%0t | done=%b | result=%b%b%b%b%b%b%b",
      $time, done, r6,r5,r4,r3,r2,r1,r0);

    $dumpfile("alu.vcd");
    $dumpvars;
  end

  // =========================
  // PRUEBAS
  // =========================
  initial begin
    clk = 0;
    reset = 0;
    bit_in = 0;
    op_select = 0;

    // -------- SUMA --------
    do_reset();
    op_select = 3'b000;
    send_data(7'b0000011, 7'b0000001); // 3 + 1
    wait(done);
    @(posedge clk);

    // -------- AND --------
    do_reset();
    op_select = 3'b001;
    send_data(7'b1010101, 7'b1110000);
    wait(done);
    @(posedge clk);

    // -------- OR --------
    do_reset();
    op_select = 3'b010;
    send_data(7'b1010101, 7'b0101010);
    wait(done);
    @(posedge clk);

    // -------- XOR --------
    do_reset();
    op_select = 3'b011;
    send_data(7'b1111111, 7'b0000000);
    wait(done);
    @(posedge clk);

    // -------- RESTA --------
    do_reset();
    op_select = 3'b100;
    send_data(7'b0000111, 7'b0000010); // 7 - 2
    wait(done);
    @(posedge clk);

    $finish;
  end

endmodule

src/alu.vcd
$date
	Sun Apr 26 01:26:41 2026
$end
$version
	Icarus Verilog
$end
$timescale
	1ps
$end
$scope module tb_ALU $end
$var wire 1 ! r6 $end
$var wire 1 " r5 $end
$var wire 1 # r4 $end
$var wire 1 $ r3 $end
$var wire 1 % r2 $end
$var wire 1 & r1 $end
$var wire 1 ' r0 $end
$var wire 1 ( done $end
$var reg 1 ) bit_in $end
$var reg 1 * clk $end
$var reg 3 + op_select [2:0] $end
$var reg 1 , reset $end
$scope module uut $end
$var wire 1 ) bit_in $end
$var wire 1 * clk $end
$var wire 1 ( done $end
$var wire 3 - op_select [2:0] $end
$var wire 1 , reset $end
$var reg 4 . bit_count [3:0] $end
$var reg 4 / count [3:0] $end
$var reg 1 0 executed $end
$var reg 1 1 flag_14 $end
$var reg 1 ' r0 $end
$var reg 1 & r1 $end
$var reg 1 % r2 $end
$var reg 1 $ r3 $end
$var reg 1 # r4 $end
$var reg 1 " r5 $end
$var reg 1 ! r6 $end
$var reg 7 2 regA [6:0] $end
$var reg 7 3 regB [6:0] $end
$var reg 7 4 result [6:0] $end
$upscope $end
$scope task do_reset $end
$upscope $end
$scope task send_data $end
$var reg 7 5 A [6:0] $end
$var reg 7 6 B [6:0] $end
$var integer 32 7 i [31:0] $end
$upscope $end
$upscope $end
$enddefinitions $end
$comment Show the parameter values. $end
$dumpall
$end
#0
$dumpvars
bx 7
bx 6
bx 5
b0 4
b0 3
b0 2
01
00
b0 /
b0 .
b0 -
1,
b0 +
0*
0)
0(
0'
0&
0%
0$
0#
0"
0!
$end
#5000
1*
#10000
0*
#15000
b1 /
b1 .
b110 7
b1 6
b11 5
0,
1*
#20000
0*
#25000
b10 .
b10 /
b101 7
1*
#30000
0*
#35000
b11 /
b11 .
b100 7
1*
#40000
0*
#45000
b100 .
b100 /
b11 7
1*
#50000
0*
#55000
b101 /
b101 .
b10 7
1*
#60000
0*
#65000
b110 .
b1 2
b110 /
1)
b1 7
1*
#70000
0*
#75000
b111 /
b111 .
b11 2
b0 7
1*
#80000
0*
#85000
b1000 .
b1000 /
0)
b110 7
1*
#90000
0*
#95000
b1001 /
b1001 .
b101 7
1*
#100000
0*
#105000
b1010 .
b1010 /
b100 7
1*
#110000
0*
#115000
b1011 /
b1011 .
b11 7
1*
#120000
0*
#125000
b1100 .
b1100 /
b10 7
1*
#130000
0*
#135000
b1101 /
b1101 .
b1 7
1*
#140000
0*
#145000
b1110 .
b1 3
1(
11
1)
b0 7
1*
#150000
0*
#155000
1%
10
b100 4
0)
b11111111111111111111111111111111 7
1*
#160000
0*
#165000
0%
00
b0 4
b0 .
b0 3
b0 2
0(
01
b0 /
1,
1*
#170000
0*
#175000
1*
#180000
0*
#185000
b1 .
b1 2
b1 /
1)
b110 7
b1110000 6
b1010101 5
b1 +
b1 -
0,
1*
#190000
0*
#195000
b10 /
b10 .
b10 2
0)
b101 7
1*
#200000
0*
#205000
b11 .
b101 2
b11 /
1)
b100 7
1*
#210000
0*
#215000
b100 /
b100 .
b1010 2
0)
b11 7
1*
#220000
0*
#225000
b101 .
b10101 2
b101 /
1)
b10 7
1*
#230000
0*
#235000
b110 /
b110 .
b101010 2
0)
b1 7
1*
#240000
0*
#245000
b111 .
b1010101 2
b111 /
1)
b0 7
1*
#250000
0*
#255000
b1000 /
b1000 .
b1 3
b110 7
1*
#260000
0*
#265000
b1001 .
b11 3
b1001 /
b101 7
1*
#270000
0*
#275000
b1010 /
b1010 .
b111 3
b100 7
1*
#280000
0*
#285000
b1011 .
b1110 3
b1011 /
0)
b11 7
1*
#290000
0*
#295000
b1100 /
b1100 .
b11100 3
b10 7
1*
#300000
0*
#305000
b1101 .
b111000 3
b1101 /
b1 7
1*
#310000
0*
#315000
1(
11
b1110 .
b1110000 3
b0 7
1*
#320000
0*
#325000
1!
1#
10
b1010000 4
b11111111111111111111111111111111 7
1*
#330000
0*
#335000
0!
0#
0(
01
b0 /
b0 .
b0 3
b0 2
00
b0 4
1,
1*
#340000
0*
#345000
1*
#350000
0*
#355000
b1 /
b1 .
b1 2
1)
b110 7
b101010 6
b10 +
b10 -
0,
1*
#360000
0*
#365000
b10 .
b10 2
b10 /
0)
b101 7
1*
#370000
0*
#375000
b11 /
b11 .
b101 2
1)
b100 7
1*
#380000
0*
#385000
b100 .
b1010 2
b100 /
0)
b11 7
1*
#390000
0*
#395000
b101 /
b101 .
b10101 2
1)
b10 7
1*
#400000
0*
#405000
b110 .
b101010 2
b110 /
0)
b1 7
1*
#410000
0*
#415000
b111 /
b111 .
b1010101 2
1)
b0 7
1*
#420000
0*
#425000
b1000 .
b1000 /
0)
b110 7
1*
#430000
0*
#435000
b1001 /
b1001 .
b1 3
1)
b101 7
1*
#440000
0*
#445000
b1010 .
b10 3
b1010 /
0)
b100 7
1*
#450000
0*
#455000
b1011 /
b1011 .
b101 3
1)
b11 7
1*
#460000
0*
#465000
b1100 .
b1010 3
b1100 /
0)
b10 7
1*
#470000
0*
#475000
b1101 /
b1101 .
b10101 3
1)
b1 7
1*
#480000
0*
#485000
b1110 .
b101010 3
1(
11
0)
b0 7
1*
#490000
0*
#495000
1!
1"
1#
1$
1%
1&
1'
10
b1111111 4
b11111111111111111111111111111111 7
1*
#500000
0*
#505000
0!
0"
0#
0$
0%
0&
0'
00
b0 4
b0 .
b0 3
b0 2
0(
01
b0 /
1,
1*
#510000
0*
#515000
1*
#520000
0*
#525000
b1 .
b1 2
b1 /
1)
b110 7
b0 6
b1111111 5
b11 +
b11 -
0,
1*
#530000
0*
#535000
b10 /
b10 .
b11 2
b101 7
1*
#540000
0*
#545000
b11 .
b111 2
b11 /
b100 7
1*
#550000
0*
#555000
b100 /
b100 .
b1111 2
b11 7
1*
#560000
0*
#565000
b101 .
b11111 2
b101 /
b10 7
1*
#570000
0*
#575000
b110 /
b110 .
b111111 2
b1 7
1*
#580000
0*
#585000
b111 .
b1111111 2
b111 /
b0 7
1*
#590000
0*
#595000
b1000 /
b1000 .
0)
b110 7
1*
#600000
0*
#605000
b1001 .
b1001 /
b101 7
1*
#610000
0*
#615000
b1010 /
b1010 .
b100 7
1*
#620000
0*
#625000
b1011 .
b1011 /
b11 7
1*
#630000
0*
#635000
b1100 /
b1100 .
b10 7
1*
#640000
0*
#645000
b1101 .
b1101 /
b1 7
1*
#650000
0*
#655000
1(
11
b1110 .
b0 7
1*
#660000
0*
#665000
1!
1"
1#
1$
1%
1&
1'
10
b1111111 4
b11111111111111111111111111111111 7
1*
#670000
0*
#675000
0!
0"
0#
0$
0%
0&
0'
0(
01
b0 /
b0 .
b0 2
00
b0 4
1,
1*
#680000
0*
#685000
1*
#690000
0*
#695000
b1 /
b1 .
b110 7
b10 6
b111 5
b100 +
b100 -
0,
1*
#700000
0*
#705000
b10 .
b10 /
b101 7
1*
#710000
0*
#715000
b11 /
b11 .
b100 7
1*
#720000
0*
#725000
b100 .
b100 /
b11 7
1*
#730000
0*
#735000
b101 /
b101 .
b1 2
1)
b10 7
1*
#740000
0*
#745000
b110 .
b11 2
b110 /
b1 7
1*
#750000
0*
#755000
b111 /
b111 .
b111 2
b0 7
1*
#760000
0*
#765000
b1000 .
b1000 /
0)
b110 7
1*
#770000
0*
#775000
b1001 /
b1001 .
b101 7
1*
#780000
0*
#785000
b1010 .
b1010 /
b100 7
1*
#790000
0*
#795000
b1011 /
b1011 .
b11 7
1*
#800000
0*
#805000
b1100 .
b1100 /
b10 7
1*
#810000
0*
#815000
b1101 /
b1101 .
b1 3
1)
b1 7
1*
#820000
0*
#825000
b1110 .
b10 3
1(
11
0)
b0 7
1*
#830000
0*
#835000
1%
1'
10
b101 4
b11111111111111111111111111111111 7
1*
